README.rst
setup.py
django_popup_forms.egg-info/PKG-INFO
django_popup_forms.egg-info/SOURCES.txt
django_popup_forms.egg-info/dependency_links.txt
django_popup_forms.egg-info/not-zip-safe
django_popup_forms.egg-info/top_level.txt
popup_forms/__init__.py
popup_forms/context_processors.py
popup_forms/decorators.py
popup_forms/models.py
popup_forms/responses.py
popup_forms/tests.py
popup_forms/templatetags/__init__.py
popup_forms/templatetags/popup_form.py