Metadata-Version: 1.0
Name: django-popup-forms
Version: 1.0.2
Summary: Django pop-up forms framework.
Home-page: http://github.com/joinourtalents/django-popup-forms
Author: Social TRM Ltd
Author-email: david@socialtrm.com
License: BSD License
Keywords: django
Platform: any
